{
    "version": "2.0.0",
    "description": "Container Signing, Verification and Storage in an OCI registry.",
    "homepage": "https://github.com/sigstore/cosign",
    "license": "Apache-2.0",
    "architecture": {
        "64bit": {
            "url": "https://github.com/sigstore/cosign/releases/download/v2.0.0/cosign-windows-amd64.exe#/cosign.exe",
            "hash": "c8f695a0c1b660c42095b90953859490dadeaedb0e88ef903f4af1fb2450f1cf"
        }
    },
    "bin": "cosign.exe",
    "checkver": "github",
    "autoupdate": {
        "architecture": {
            "64bit": {
                "url": "https://github.com/sigstore/cosign/releases/download/v$version/cosign-windows-amd64.exe#/cosign.exe"
            }
        },
        "hash": {
            "url": "$baseurl/cosign_checksums.txt"
        }
    }
}
