{
    "version": "133.0.3050.0",
    "description": "Close the loop on your developer cycle by automating testing of your website in Microsoft Edge (Chromium).",
    "homepage": "https://developer.microsoft.com/en-us/microsoft-edge/tools/webdriver",
    "license": {
        "identifier": "Freeware",
        "url": "https://az813057.vo.msecnd.net/webdriver/license.html"
    },
    "notes": "For legacy (EdgeHTML) version, see 'versions/edgedriver-legacy'.",
    "architecture": {
        "64bit": {
            "url": "https://msedgedriver.azureedge.net/133.0.3050.0/edgedriver_win64.zip",
            "hash": "0673543fd54e7c2676bf78a4f5306a0a30d784e209e0ca32c6fa2afd53715b22"
        },
        "32bit": {
            "url": "https://msedgedriver.azureedge.net/133.0.3050.0/edgedriver_win32.zip",
            "hash": "6cda8b8b809199a3d2fb3fab99154c9203c5079197e74a1c6bab5c156c6cc84a"
        }
    },
    "bin": "msedgedriver.exe",
    "checkver": {
        "url": "https://msedgedriver.azureedge.net/LATEST_CANARY",
        "regex": "([\\d.]+)"
    },
    "autoupdate": {
        "architecture": {
            "64bit": {
                "url": "https://msedgedriver.azureedge.net/$version/edgedriver_win64.zip"
            },
            "32bit": {
                "url": "https://msedgedriver.azureedge.net/$version/edgedriver_win32.zip"
            }
        }
    }
}
